awesome_admin/__init__.py
django_awesome_admin-0.1.0.dist-info/METADATA
django_awesome_admin-0.1.0.dist-info/WHEEL
django_awesome_admin-0.1.0.dist-info/RECORD
